easydata/__init__.py
easydata/cli.py
easydata/dataio.py
easydata/decorator.py
easydata/ui.py
easydata_ds-0.1.0.dist-info/licenses/LICENSE
easydata_ds-0.1.0.dist-info/METADATA
easydata_ds-0.1.0.dist-info/WHEEL
easydata_ds-0.1.0.dist-info/entry_points.txt
easydata_ds-0.1.0.dist-info/top_level.txt
easydata_ds-0.1.0.dist-info/RECORD
