Metadata-Version: 2.4
Name: easydata-ds
Version: 0.1.0
Summary: A Python library for data scientists to easily apply functions to datasets with a terminal UI
Home-page: https://github.com/coleragone/easydata
Author: Cole Ragone
Author-email: Cole Ragone <coleragone@example.com>
Maintainer-email: Cole Ragone <coleragone@example.com>
License: MIT
Project-URL: Homepage, https://github.com/coleragone/easydata
Project-URL: Documentation, https://github.com/coleragone/easydata#readme
Project-URL: Repository, https://github.com/coleragone/easydata
Project-URL: Bug Tracker, https://github.com/coleragone/easydata/issues
Keywords: data science,pandas,terminal ui,data processing,decorator
Classifier: Development Status :: 3 - Alpha
Classifier: Intended Audience :: Science/Research
Classifier: Intended Audience :: Developers
Classifier: Topic :: Scientific/Engineering :: Information Analysis
Classifier: Topic :: Software Development :: Libraries :: Python Modules
Classifier: License :: OSI Approved :: MIT License
Classifier: Programming Language :: Python :: 3
Classifier: Programming Language :: Python :: 3.7
Classifier: Programming Language :: Python :: 3.8
Classifier: Programming Language :: Python :: 3.9
Classifier: Programming Language :: Python :: 3.10
Classifier: Programming Language :: Python :: 3.11
Classifier: Programming Language :: Python :: 3.12
Classifier: Operating System :: OS Independent
Requires-Python: >=3.7
License-File: LICENSE
Requires-Dist: pandas>=1.0.0
Requires-Dist: rich>=10.0.0
Requires-Dist: click>=8.0.0
Requires-Dist: tqdm>=4.60.0
Provides-Extra: dev
Requires-Dist: pytest>=6.0; extra == "dev"
Requires-Dist: pytest-cov; extra == "dev"
Requires-Dist: black; extra == "dev"
Requires-Dist: flake8; extra == "dev"
Requires-Dist: mypy; extra == "dev"
Requires-Dist: build; extra == "dev"
Requires-Dist: twine; extra == "dev"
Dynamic: author
Dynamic: home-page
Dynamic: license-file
Dynamic: requires-python
